google_gax-0.15.16-py2.7-nspkg.pth
google/gapic/__init__.py
google/gapic/longrunning/__init__.py
google/gapic/longrunning/operations_client.py
google/gapic/longrunning/operations_client_config.json
google/gax/__init__.py
google/gax/_grpc_google_auth.py
google/gax/api_callable.py
google/gax/bundling.py
google/gax/config.py
google/gax/errors.py
google/gax/grpc.py
google/gax/path_template.py
google/gax/retry.py
google/gax/utils/__init__.py
google/gax/utils/messages.py
google/gax/utils/metrics.py
google/gax/utils/oneof.py
google/gax/utils/protobuf.py
google_gax-0.15.16.dist-info/DESCRIPTION.rst
google_gax-0.15.16.dist-info/METADATA
google_gax-0.15.16.dist-info/RECORD
google_gax-0.15.16.dist-info/WHEEL
google_gax-0.15.16.dist-info/metadata.json
google_gax-0.15.16.dist-info/namespace_packages.txt
google_gax-0.15.16.dist-info/top_level.txt
